VERSION
alman/__init__.py
alman/apibits/__init__.py
alman/apibits/api_client.py
alman/apibits/api_endpoint.py
alman/apibits/api_list.py
alman/apibits/api_method.py
alman/apibits/api_resource.py
alman/apibits/errors.py
alman/apibits/headers_builder.py
alman/apibits/params_builder.py
alman/apibits/path_builder.py
alman/apibits/requester.py
alman/apibits/version.py
alman/endpoints/__init__.py
alman/endpoints/bookings.py
alman/endpoints/calendar_vacancies.py
alman/endpoints/calendars.py
alman/endpoints/vacancies.py
alman/endpoints/vacancy_bookings.py
alman/resources/__init__.py
alman/resources/booking.py
alman/resources/calendar.py
alman/resources/vacancy.py
alman/test/__init__.py
alman/test/test_api_list.py
alman/test/test_api_method.py
alman/test/test_headers_builder.py
alman/test/test_params_builder.py
alman/test/test_path_builder.py
alman/test/test_requester.py
alman-0.0.1.dist-info/DESCRIPTION.rst
alman-0.0.1.dist-info/METADATA
alman-0.0.1.dist-info/metadata.json
alman-0.0.1.dist-info/RECORD
alman-0.0.1.dist-info/top_level.txt
alman-0.0.1.dist-info/WHEEL
