Metadata-Version: 1.0
Name: alman
Version: 0.0.1
Summary: Alman is a calendar scheduling API.
Home-page: http://almanapi.com/docs
Author: UNKNOWN
Author-email: support@almanapi.com
License: UNKNOWN
Platform: UNKNOWN
